sparkplug_files/__init__.py
sparkplug_files/apps.py
sparkplug_files/migrations/0001_initial.py
sparkplug_files/migrations/__init__.py
sparkplug_files/models/__init__.py
sparkplug_files/models/file.py
sparkplug_files/permissions/__init__.py
sparkplug_files/permissions/file.py
sparkplug_files/serializers/__init__.py
sparkplug_files/serializers/file_expanded.py
sparkplug_files/serializers/file_teaser.py
sparkplug_files/serializers/file_write.py
sparkplug_files/signals.py
sparkplug_files/uploads.py
sparkplug_files/urls.py
sparkplug_files/views/__init__.py
sparkplug_files/views/file.py
sparkplug_api_files-1.0.4.dist-info/METADATA
sparkplug_api_files-1.0.4.dist-info/WHEEL
sparkplug_api_files-1.0.4.dist-info/RECORD
